olm/__init__.py
olm/core/__init__.py
olm/core/checkpoint.py
olm/core/config.py
olm/core/dist.py
olm/core/dtype.py
olm/core/registry.py
olm/core/utils.py
olm/data/__init__.py
olm/data/collate.py
olm/data/datasets/__init__.py
olm/data/datasets/base_dataset.py
olm/data/datasets/data_loader.py
olm/data/datasets/hf_dataset.py
olm/data/datasets/local_dataset.py
olm/data/tokenization/__init__.py
olm/data/tokenization/base.py
olm/data/tokenization/hf_tokenizer.py
olm/data/tokenization/hf_train_custom.py
olm/export/__init__.py
olm/export/hf_convert.py
olm/export/onnx_torchscript.py
olm/logging/__init__.py
olm/logging/logger.py
olm/logging/progress.py
olm/models/alibaba/__init__.py
olm/models/alibaba/qwen2.py
olm/models/allenai/__init__.py
olm/models/allenai/olmo.py
olm/models/facebook/__init__.py
olm/models/facebook/opt.py
olm/models/google/__init__.py
olm/models/google/gemma2.py
olm/models/meta/__init__.py
olm/models/meta/llama2.py
olm/models/meta/llama3.py
olm/models/microsoft/__init__.py
olm/models/microsoft/phi3.py
olm/models/microsoft/phi4.py
olm/models/openai/__init__.py
olm/models/openai/gpt2.py
olm/nn/__init__.py
olm/nn/torch_nn_wrappers.py
olm/nn/activations/__init__.py
olm/nn/activations/base.py
olm/nn/activations/clu.py
olm/nn/activations/elu.py
olm/nn/activations/geglu.py
olm/nn/activations/gelu.py
olm/nn/activations/glu.py
olm/nn/activations/identity.py
olm/nn/activations/leaky_relu.py
olm/nn/activations/liglu.py
olm/nn/activations/mish.py
olm/nn/activations/prelu.py
olm/nn/activations/reglu.py
olm/nn/activations/relu.py
olm/nn/activations/selu.py
olm/nn/activations/sigmoid.py
olm/nn/activations/silu.py
olm/nn/activations/softmax.py
olm/nn/activations/softplus.py
olm/nn/activations/swiglu.py
olm/nn/activations/tanh.py
olm/nn/attention/__init__.py
olm/nn/attention/alibi.py
olm/nn/attention/base.py
olm/nn/attention/flash.py
olm/nn/attention/gqa.py
olm/nn/attention/linear_attn.py
olm/nn/attention/mha.py
olm/nn/blocks/LM.py
olm/nn/blocks/__init__.py
openlanguagemodel-1.0.dist-info/licenses/LICENSE
openlanguagemodel-1.0.dist-info/METADATA
openlanguagemodel-1.0.dist-info/WHEEL
openlanguagemodel-1.0.dist-info/top_level.txt
openlanguagemodel-1.0.dist-info/RECORD
