Metadata-Version: 2.4
Name: openlanguagemodel
Version: 1.0
Summary: OpenLanguageModel (OLM): A clean library based off pytorch to quickly implement LLMs with custom architectures.
Author: OpenLanguageModel Team
License: MIT
Project-URL: Homepage, https://github.com/openlanguagemodel/openlanguagemodel
Project-URL: Repository, https://github.com/openlanguagemodel/openlanguagemodel
Project-URL: Issues, https://github.com/openlanguagemodel/openlanguagemodel/issues
Keywords: deep learning,machine learning,language models,transformers,pytorch,llm
Classifier: Development Status :: 3 - Alpha
Classifier: Intended Audience :: Developers
Classifier: Intended Audience :: Science/Research
Classifier: License :: OSI Approved :: MIT License
Classifier: Programming Language :: Python :: 3
Classifier: Programming Language :: Python :: 3.8
Classifier: Programming Language :: Python :: 3.9
Classifier: Programming Language :: Python :: 3.10
Classifier: Programming Language :: Python :: 3.11
Classifier: Topic :: Scientific/Engineering :: Artificial Intelligence
Requires-Python: >=3.8
License-File: LICENSE
Requires-Dist: torch>=2.0.0
Requires-Dist: numpy>=1.20.0
Requires-Dist: tqdm>=4.60.0
Requires-Dist: pyyaml>=6.0
Requires-Dist: transformers>=4.57.1
Requires-Dist: datasets>=2.0.0
Provides-Extra: dev
Requires-Dist: pytest>=7.0.0; extra == "dev"
Requires-Dist: black>=22.0.0; extra == "dev"
Requires-Dist: flake8>=4.0.0; extra == "dev"
Requires-Dist: mypy>=0.950; extra == "dev"
Requires-Dist: mkdocs>=1.5.0; extra == "dev"
Requires-Dist: mkdocs-material>=9.0.0; extra == "dev"
Requires-Dist: mkdocstrings[python]>=0.24.0; extra == "dev"
Requires-Dist: build; extra == "dev"
Requires-Dist: twine; extra == "dev"
Provides-Extra: flash
Requires-Dist: flash-attn>=2.0.0; extra == "flash"
Dynamic: license-file
